{
  "goal": "KidQuest：給 8–12 歲孩子的每日任務 RPG 網頁遊戲（《我獨自升級》暗黑系統風格）— 完成現實任務換 EXP/金幣，升級配點、技能樹、傳送門、商店與真實獎勵",
  "version": "2.1",
  "created_at": "2026-06-13T00:00:00Z",
  "mode": "full",
  "is_ui": true,
  "current_milestone_id": 19,
  "planning_complete": true,
  "budget": {
    "used_usd": 6.9,
    "limit_usd": 30.0,
    "tokens_used": 0,
    "planning_calls": 2,
    "execution_calls": 3,
    "verification_calls": 3,
    "cost_estimate_usd": {
      "planning": 1.5,
      "execution": 1.0,
      "verification": 0.8
    }
  },
  "milestones": [
    {
      "id": 1,
      "title": "核心骨架與存檔系統",
      "spec_file": "milestones/backfill-v3.md",
      "spec_summary": "單檔 HTML/Vanilla JS 架構；localStorage(kidquest_data) 存讀檔；v1/v2→v3 自動遷移；覺醒登錄（名稱/職業）。",
      "status": "complete",
      "attempts": 1,
      "max_attempts": 3,
      "require_human_approval": false,
      "depends_on": [],
      "acceptance_criteria": [
        "進度自動存入 localStorage 並可正確讀回",
        "v1/v2 舊存檔自動遷移到 v3 且保留等級/金幣/點數/技能/裝備/成就/PIN/紀錄",
        "首次啟動可登錄獵人名稱與職業（魔法師/戰士/守護騎士）"
      ],
      "human_feedback": null,
      "history": [
        { "timestamp": "2026-06-13T00:00:00Z", "automated_tests": "PASS", "ai_verification": "PASS: backfilled — 由 test/smoke.js 65/65 通過驗證" }
      ]
    },
    {
      "id": 2,
      "title": "任務系統",
      "spec_file": "milestones/backfill-v3.md",
      "spec_summary": "49 個任務的任務池（7 類）；每日抽選 8 個（E×3/C×3/B×2）+ 每週 S×2；今日時段推薦；挑戰完成→審核→發獎；每日重置與一鍵重抽。",
      "status": "complete",
      "attempts": 1,
      "max_attempts": 3,
      "require_human_approval": false,
      "depends_on": [1],
      "acceptance_criteria": [
        "每日自動從任務池抽出正確數量與等級分布的今日任務",
        "完成任務進入待審核，核准後發放對應報酬",
        "每日重置與一鍵重抽今日任務正常運作"
      ],
      "human_feedback": null,
      "history": [
        { "timestamp": "2026-06-13T00:00:00Z", "automated_tests": "PASS", "ai_verification": "PASS: backfilled — 由 test/smoke.js 65/65 通過驗證" }
      ]
    },
    {
      "id": 3,
      "title": "成長系統",
      "spec_file": "milestones/backfill-v3.md",
      "spec_summary": "升級每級 +3 能力點（力/敏/智/活/感，各有實效）+1 技能點；三職業各 7 技能依序解鎖；20 個獵人成就解鎖送獎。",
      "status": "complete",
      "attempts": 1,
      "max_attempts": 3,
      "require_human_approval": false,
      "depends_on": [1],
      "acceptance_criteria": [
        "升級正確發放能力點與技能點，配點影響實際效果",
        "三職業技能樹依序解鎖",
        "成就條件達成時解鎖並發放獎勵"
      ],
      "human_feedback": null,
      "history": [
        { "timestamp": "2026-06-13T00:00:00Z", "automated_tests": "PASS", "ai_verification": "PASS: backfilled — 由 test/smoke.js 65/65 通過驗證" }
      ]
    },
    {
      "id": 4,
      "title": "經濟與獎勵系統",
      "spec_file": "milestones/backfill-v3.md",
      "spec_summary": "金幣經濟節奏；44 項商店道具（含 5 套裝、類型篩選、感知折扣）；保護券（購買/成就贈送/抵消中斷）；連續紀錄報酬加成；15 個真實獎勵。",
      "status": "complete",
      "attempts": 1,
      "max_attempts": 3,
      "require_human_approval": false,
      "depends_on": [2, 3],
      "acceptance_criteria": [
        "商店購買與類型篩選、感知折扣正確運作",
        "連續紀錄加成與保護券抵消邏輯正確",
        "真實獎勵可瀏覽與兌換"
      ],
      "human_feedback": null,
      "history": [
        { "timestamp": "2026-06-13T00:00:00Z", "automated_tests": "PASS", "ai_verification": "PASS: backfilled — 由 test/smoke.js 65/65 通過驗證" }
      ]
    },
    {
      "id": 5,
      "title": "管理者（家長）模式",
      "spec_file": "milestones/backfill-v3.md",
      "spec_summary": "PIN 鎖（預設 1234）；任務審核核准/退回；任務池管理（啟停/排程/年齡/增刪改）；今日任務設定；保護券核可；真實獎勵管理；本週統計、紀錄、重設 PIN/資料。",
      "status": "complete",
      "attempts": 1,
      "max_attempts": 3,
      "require_human_approval": false,
      "depends_on": [2, 4],
      "acceptance_criteria": [
        "PIN 正確保護管理者功能且可重設",
        "家長可審核任務、管理任務池與今日任務設定",
        "保護券使用需家長核可"
      ],
      "human_feedback": null,
      "history": [
        { "timestamp": "2026-06-13T00:00:00Z", "automated_tests": "PASS", "ai_verification": "PASS: backfilled — 由 test/smoke.js 65/65 通過驗證" }
      ]
    },
    {
      "id": 6,
      "title": "UI／視覺與傳送門地圖",
      "spec_file": "milestones/backfill-v3.md",
      "spec_summary": "暗黑系統介面（Tailwind CDN + Noto Sans TC/Rajdhani）；發光特效與 emoji；今日任務化身傳送門地圖（E/C/B/S 篩選、S 級 DUNGEON BREAK）；375px–1200px RWD。",
      "status": "complete",
      "attempts": 1,
      "max_attempts": 3,
      "require_human_approval": false,
      "depends_on": [2],
      "acceptance_criteria": [
        "暗黑系統風格介面與發光特效正常呈現",
        "傳送門地圖可依等級篩選，S 級有特殊呈現",
        "手機 375px 到桌機 1200px 響應式版面正常"
      ],
      "human_feedback": null,
      "history": [
        { "timestamp": "2026-06-13T00:00:00Z", "automated_tests": "PASS", "ai_verification": "PASS: backfilled — 由 test/smoke.js 65/65 通過驗證" }
      ]
    },
    {
      "id": 7,
      "title": "PWA 安裝與離線快取（提案）",
      "spec_file": "milestones/m7-pwa-offline.md",
      "spec_summary": "加入 manifest 與 service worker，讓遊戲可安裝到主畫面並完整離線執行；不改變既有玩法與存檔。",
      "status": "complete",
      "attempts": 1,
      "max_attempts": 3,
      "require_human_approval": false,
      "depends_on": [1],
      "acceptance_criteria": [
        "可從瀏覽器『加入主畫面』安裝為 PWA",
        "離線（無網路）時仍可開啟並正常遊玩",
        "既有 localStorage 存檔與 65 項煙霧測試不受影響"
      ],
      "human_feedback": null,
      "history": [
        { "timestamp": "2026-06-13T00:00:00Z", "automated_tests": "PASS", "ai_verification": "PASS: 新增 manifest.webmanifest / sw.js / icon.svg + head 連結與 SW 註冊；smoke 65/65 維持；PWA 需經 http(s)/localhost 提供（已於 README 註明）" }
      ]
    },
    {
      "id": 8,
      "title": "跨裝置存檔轉移（匯出/匯入，輕量方案）",
      "spec_file": "milestones/m8-cloud-sync.md",
      "spec_summary": "純本機匯出/匯入存檔（無帳號、不上傳），作為離線轉移與備援。真正的帳號制雲端同步改由 M9 處理。",
      "status": "complete",
      "attempts": 1,
      "max_attempts": 3,
      "require_human_approval": true,
      "depends_on": [1, 7],
      "acceptance_criteria": [
        "可在裝置間轉移存檔並在另一裝置還原（以匯出/匯入檔案實現）",
        "未登入時遊戲行為與現在完全相同（純本機）",
        "兒童個資處理符合隱私原則（此方案為零蒐集、不上傳）"
      ],
      "human_feedback": null,
      "history": [
        { "timestamp": "2026-06-13T00:00:00Z", "automated_tests": "PASS", "ai_verification": "PASS: 管理者面板新增匯出/匯入存檔；跨裝置轉移可行、未登入行為不變、零個資蒐集；smoke 65/65。輕量方案結案；真正的帳號制雲端同步轉由 M9 處理。" }
      ]
    },
    {
      "id": 9,
      "title": "帳號制雲端同步（Supabase + Google 登入）",
      "spec_file": "milestones/m9-cloud-sync-supabase.md",
      "spec_summary": "每位小孩用自己的 Google 帳號登入，進度存到 Supabase 並以 Row Level Security 個別隔離；自動跨裝置同步。未登入時維持純本機。先 Mockup + 設定包供審核，核准且使用者開好 Supabase 專案後再整合。",
      "status": "blocked",
      "attempts": 1,
      "max_attempts": 3,
      "require_human_approval": true,
      "depends_on": [1],
      "human_feedback": "已被取代（superseded）：2026-06-16 使用者決定改造為小型多人線上遊戲。家長 Gmail 登入 + 小孩子帳號 + 雲端同步的需求改由 M17（家長為主帳號模型重構）與 M23（真正的 Supabase/Google OAuth 接線，human-approval gate）承接。schema.sql 與設定包仍可沿用。此里程碑標 blocked 以排除於自動推進，勿再單獨啟動。",
      "acceptance_criteria": [
        "小孩用自己的 Google 帳號登入後，進度自動同步到雲端並可在另一裝置還原",
        "不同帳號的進度各自獨立儲存且互相看不到（Supabase RLS）",
        "未登入時遊戲行為與現在完全相同（純本機、可離線）",
        "雲端設定缺失時自動退回純本機，且 65 項煙霧測試維持綠燈"
      ],
      "history": [
        { "timestamp": "2026-06-13T00:00:00Z", "automated_tests": "N/A", "ai_verification": "DEFERRED: 暫緩，改先做單機可攜桌面版（M10）；Mockup 與 Supabase 設定包已備妥，日後可直接續接。" }
      ]
    },
    {
      "id": 10,
      "title": "單機可攜桌面版（Electron，存檔隨資料夾移動）",
      "spec_file": "milestones/m10-desktop-portable.md",
      "spec_summary": "用 Electron 把遊戲包成桌面 App，可從資料夾內的 .exe 執行；帳號與進度存成 .exe 同層的 kidquest-save.json，整包搬到別處只要存檔在就能接續玩。瀏覽器版維持可用。",
      "status": "complete",
      "attempts": 1,
      "max_attempts": 3,
      "require_human_approval": false,
      "depends_on": [1],
      "acceptance_criteria": [
        "可從資料夾內的 .exe 啟動遊戲（不需另開瀏覽器）",
        "帳號與進度存成 .exe 同層的存檔檔案，移動整包資料夾後進度不遺失、可接續",
        "未在 Electron 環境（純瀏覽器）時仍以 localStorage 正常運作",
        "node test/smoke.js 維持 65/65"
      ],
      "human_feedback": null,
      "history": [
        { "timestamp": "2026-06-13T00:00:00Z", "automated_tests": "PASS", "ai_verification": "PASS: Electron 桌面外殼 + 檔案式存檔橋接（preload window.kqStore）。已打包 dist/KidQuest-win32-x64/KidQuest.exe 並實機啟動成功（4 進程）；新增 test/desktop-save.test.js 驗證存檔寫入資料夾並於『搬到另一資料夾』後接續（4/4）；smoke 維持 65/65。註：桌面版樣式仍走 CDN，完全離線需在地化資源（可另立里程碑）。" }
      ]
    },
    {
      "id": 11,
      "title": "本地多帳號登入／登出／切換（密碼）",
      "spec_file": "milestones/m11-local-accounts.md",
      "spec_summary": "本機多帳號系統：每個帳號各自進度、可設密碼，啟動顯示登入閘門，遊戲內可登出與切換帳號。全部存本地（kidquest-accounts.json + 各帳號存檔），不影響既有單存檔與測試。",
      "status": "complete",
      "attempts": 1,
      "max_attempts": 3,
      "require_human_approval": false,
      "depends_on": [10],
      "human_feedback": null,
      "acceptance_criteria": [
        "啟動時若已有帳號則顯示登入畫面，可選帳號並用密碼登入",
        "可建立多個帳號，各帳號進度互相獨立",
        "遊戲內可登出並切換到另一帳號，進度不混淆",
        "可設定／變更帳號密碼；空密碼帳號可直接登入",
        "無帳號時沿用原本流程；node test/smoke.js 維持綠燈"
      ],
      "history": [
        { "timestamp": "2026-06-13T00:00:00Z", "automated_tests": "PASS", "ai_verification": "PASS: 新增登入閘門 + 帳號系統（建立/登入/登出/切換/密碼雜湊/刪除），活躍帳號資料留在 kidquest_data、帳號清單與快照存 kidquest_accounts。切換時先快照再載入，進度互相隔離。新增 test/accounts.test.js（10/10）；smoke 69/69、desktop-save 4/4；桌面 exe 重新打包並實機啟動成功。" }
      ]
    },
    {
      "id": 12,
      "title": "經濟系統重整（金錢／真實獎勵換算／RPG 平衡）",
      "spec_file": "milestones/m12-economy-overhaul.md",
      "spec_summary": "集中 ECONOMY 設定；真實獎勵以台幣家庭預算定價（5🪙≈NT$1）並改為申請→家長核准/退回退款；虛擬道具改 RPG 稀有度定價；重調 DIFFS 與升級曲線；連續加成拆 EXP/金幣兩套；完全移除連續紀錄保護券。",
      "status": "complete",
      "attempts": 1,
      "max_attempts": 3,
      "require_human_approval": false,
      "depends_on": [3, 4],
      "acceptance_criteria": [
        "新增 ECONOMY 設定；DIFFS 改 E12/8、C28/18、B60/35、S140/100；每日 3E3C2B 基礎約 148 金幣",
        "連續加成拆開：EXP +10%/天（上限+100%）、金幣 +5%/天（上限+50%）；今日全完成 +25 金幣 +20% EXP",
        "真實獎勵 estimatedTwd/cost=twd×5/tier；兌換為 requested→approved/rejected（退回退還金幣）；家長見台幣估值與月預算提醒，孩子只見金幣與約需天數",
        "虛擬道具改 RPG 稀有度定價（common/rare/epic/legendary），不顯示台幣；升級曲線改 xpNeed(level)",
        "完全移除連續紀錄保護券（商品/邏輯/成就/UI/測試）；smoke 69/69 + 桌面存檔測試通過"
      ],
      "human_feedback": null,
      "history": [
        { "timestamp": "2026-06-13T00:00:00Z", "automated_tests": "PASS", "ai_verification": "PASS: 全面重整經濟（ECONOMY 設定、DIFFS、xpNeed 曲線、拆分連續加成、真實獎勵申請/核准/退款流程、RPG 商店定價、狀態頁與家長頁經濟面板），並徹底移除保護券。新增遷移 v3→v4。smoke 69/69、desktop-save 4/4 通過。" }
      ]
    },
    {
      "id": 13,
      "title": "任務池擴充（100 任務／8 分類／6 難度／年齡性別）+ 1080p 桌面",
      "spec_file": "milestones/m13-task-pool-expansion.md",
      "spec_summary": "TASK_POOL 擴充為 100 個適齡（5–15）任務，新增 8 大分類與 6 級難度（E/D/C/B/A/S）；任務含 ageRange/estimatedMinutes/why/repeatRule；可設定孩子年齡與性別並據此抽選；家長可啟用停用、由每日抽選系統挑選；桌面版改 1920×1080 視窗模式。",
      "status": "complete",
      "attempts": 1,
      "max_attempts": 3,
      "require_human_approval": false,
      "depends_on": [3, 10],
      "acceptance_criteria": [
        "TASK_POOL 達 100 個任務，分布 E20/D20/C20/B15/A15/S10，涵蓋 8 大分類，內容貼近台灣家庭與學校、鼓勵成長不含危險/羞辱/過度控制/侵犯隱私",
        "難度 easy=E/normal=D/medium=C/hard=B/epic=A/super=S；E/D/C/B 進每日抽選，A/S 為每週挑戰",
        "可在覺醒與管理者模式設定孩子年齡（5–15）與性別，任務依 ageRange/gender 篩選",
        "任務不全顯示於每日畫面，而由家長啟用停用 + 每日抽選系統挑選",
        "桌面版 1920×1080 視窗模式；smoke 75/75、desktop-save 4/4、accounts 10/10"
      ],
      "human_feedback": null,
      "history": [
        { "timestamp": "2026-06-13T00:00:00Z", "automated_tests": "PASS", "ai_verification": "PASS: 重建 TASK_POOL 為 100 個適齡任務（8 分類、6 難度、ageRange/estimatedMinutes/why/repeatRule）；新增 normal(D)/super(S) 難度與 CHALLENGE 集合；ageMatch 改用 ageRange+gender；玩家加 age/gender 並可於覺醒與家長頁設定；每日抽選改 E/D/C/B 平均分配、A/S 每週挑戰；地圖/分頁/成就/職業加成同步更新；Electron 視窗改 1920×1080。smoke 75/75、desktop-save 4/4、accounts 10/10，exe 重新打包並啟動成功。" }
      ]
    },
    {
      "id": 14,
      "title": "寬版 PC 佈局 + 頂部帳號/家長列 + 隱藏孩子台幣 + 擴充裝備獎勵",
      "spec_file": "milestones/m14-pc-layout-topbar.md",
      "spec_summary": "桌面採左側欄導覽 + 寬版內容（行動仍為底部導覽）；視窗頂部常駐帳號(登出/切換)與家長登入，不需從家長功能進入；孩子畫面移除台幣金額（NT 估值僅家長可見）；商店裝備 43→58、真實獎勵 15→25。",
      "status": "complete",
      "attempts": 1,
      "max_attempts": 3,
      "require_human_approval": false,
      "depends_on": [11, 12, 13],
      "acceptance_criteria": [
        "桌面（≥1024px）採左側欄主導覽 + 寬版內容區（max-w-5xl/6xl）；行動裝置維持底部導覽直式佈局",
        "視窗頂部列常駐帳號（點擊登出/切換）與家長登入；切換帳號不再需要從家長功能進入",
        "孩子畫面不顯示任何台幣金額；本月已核准真實獎勵 NT$ 僅家長模式可見（= 家長核准的兌換申請 estimatedTwd 總和）",
        "商店虛擬道具擴充至 58 項、真實獎勵擴充至 25 項",
        "桌面 exe 重新打包並啟動成功；smoke 75/75、desktop-save 4/4、accounts 10/10"
      ],
      "human_feedback": null,
      "history": [
        { "timestamp": "2026-06-13T00:00:00Z", "automated_tests": "PASS", "ai_verification": "PASS: 新增固定頂部列（帳號切換/家長登入）與桌面左側欄導覽 + 寬版內容（CSS @media ≥1024px）；renderTop 同步頂部列；孩子狀態頁第三格由 NT$ 改為『本月已兌換獎勵』次數（台幣僅家長頁）；SHOP_ITEMS 加 15 件(共58)、DEFAULT_REWARDS 加 10 個(共25)；smoke/desktop/accounts 全綠，exe 1080p 寬版啟動成功。" }
      ]
    },
    {
      "id": 15,
      "title": "家長帳號/獎勵/PIN 管理強化 + 使用者密碼 + 裝備賣回 + 移除重置鈕",
      "spec_file": "milestones/m15-parent-controls-and-sell.md",
      "spec_summary": "家長可變更/刪除任何帳號、編輯真實獎勵名稱與點數、變更 PIN；使用者可自設密碼；真實獎勵維持申請→核准/退回退款；背包裝備可賣回商店返還半價；移除『重置所有資料』按鈕；狀態頁背包/成就移到主選單、移除狀態頁家長鈕。",
      "status": "complete",
      "attempts": 1,
      "max_attempts": 3,
      "require_human_approval": false,
      "depends_on": [11, 12, 14],
      "acceptance_criteria": [
        "家長可刪除任一帳號（含登入中）並可變更任一帳號密碼；家長 PIN 可變更",
        "使用者可在狀態頁自設/變更自己的帳號密碼",
        "真實獎勵購買為申請制，家長否決時全額退還金幣（沿用 M12）",
        "移除『重置所有資料』按鈕；家長後台可編輯真實獎勵名稱與所需點數",
        "狀態頁背包/成就移至主選單、移除狀態頁家長鈕；背包裝備可賣回商店返還半價",
        "smoke 77/77、desktop-save 4/4、accounts 10/10，exe 重新打包啟動成功"
      ],
      "human_feedback": null,
      "history": [
        { "timestamp": "2026-06-13T00:00:00Z", "automated_tests": "PASS", "ai_verification": "PASS: setAccountPassword(id)/deleteAccount(id) 改為可操作任一帳號（刪除登入中帳號後回登入畫面）；新增 setMyPassword 與狀態頁『設定我的密碼』；真實獎勵表單支援編輯名稱/點數（estimatedTwd 連動）；新增 sellItem 返還半價並記錄；移除 resetData 按鈕與函式；主選單加背包/成就、狀態頁移除背包/成就/家長三鈕。smoke 77/77、desktop 4/4、accounts 10/10，exe 啟動成功。" }
      ]
    },
    {
      "id": 16,
      "title": "雲端部署上線（GitHub + Vercel）+ PWA 安裝 QR code",
      "spec_file": "milestones/m16-deploy-github-vercel-pwa.md",
      "spec_summary": "建立 GitHub public repo（JerryChou0218/AllRiseKids）並推送全部歷史；Vercel 正式部署 allrisekids.vercel.app（連 GitHub 自動部署）；vercel.json builds 改 **/* 修 install/圖示 404；.vercelignore 排除 node_modules/dist 避開 100MB 上限；sharp 由 SVG 產 192/512 PNG 圖示供 iOS；新增 install.html QR code 安裝頁（iOS/Android 加入主畫面步驟）。",
      "status": "complete",
      "attempts": 1,
      "max_attempts": 3,
      "require_human_approval": false,
      "depends_on": [7, 15],
      "human_feedback": null,
      "acceptance_criteria": [
        "程式碼推送到 GitHub public repo（JerryChou0218/AllRiseKids），含 M1–M15 完整 commit 歷史",
        "Vercel 正式環境部署成功，https://allrisekids.vercel.app 可開啟並正常遊玩",
        "https://allrisekids.vercel.app/install.html 可開啟，含可掃描 QR code 與 iOS/Android 加入主畫面步驟",
        "manifest.webmanifest 含 192/512 PNG 圖示（iOS Safari 主畫面圖示相容）",
        "既有行為不受影響：smoke 77/77、accounts 10/10、desktop-save 4/4 全綠"
      ],
      "history": [
        { "timestamp": "2026-06-16T00:00:00Z", "automated_tests": "PASS", "ai_verification": "PASS: GitHub repo 建立並推送（gh CLI）；Vercel --prod 部署成功並 alias allrisekids.vercel.app；vercel.json builds 由 index.html 改 **/* 修正 install.html/圖示 404；.vercelignore 排除 node_modules(563MB)/dist(268MB) 避開 100MB 上限；sharp 由 icon.svg 產 icon-192/512.png 並寫入 manifest（iOS 相容）；新增 install.html QR code 安裝頁。順帶修兩個 M15 之後引入的既有測試回歸（accounts mock 補 focus()、setAccountPassword 改 modal 流程後測試同步更新）。smoke 77/77、accounts 10/10、desktop-save 4/4 全綠。" }
      ]
    },
    {
      "id": 17,
      "title": "帳號模型重構：家長為主帳號（Gmail）+ 小孩子帳號（最多 4）+ 雲端就緒抽象層",
      "spec_file": "milestones/m17-parent-child-account-model.md",
      "spec_summary": "安裝後第一畫面只開放家長以 Gmail 註冊/登入；家長為 root，底下建立最多 4 個小孩子帳號。小孩切換需先登出小孩；小孩無法登出家長（家長登出只在家長頁）。導入 cloudStore 抽象層（先本機實作、介面對齊 Supabase），所有小孩資料掛在家長帳號下。整個 init/gate 流程重寫。",
      "status": "complete",
      "attempts": 1,
      "max_attempts": 3,
      "require_human_approval": false,
      "depends_on": [11, 15],
      "human_feedback": null,
      "acceptance_criteria": [
        "安裝後第一畫面為家長登入/註冊，目前只開放 Gmail（OAuth 先以本機 stub 模擬，介面對齊真實 Google 登入）",
        "家長可建立最多 4 個小孩子帳號；超過 4 個時阻擋並提示",
        "小孩之間切換需先登出目前小孩再選另一個；小孩端無任何可登出家長的入口",
        "家長登出只在家長頁面提供；登出家長後回到家長登入畫面",
        "所有小孩進度資料掛在家長帳號物件下（parent.children[]），透過 cloudStore 抽象層讀寫；雲端設定缺失時自動走本機",
        "既有單人/桌面行為相容；smoke、accounts、desktop-save 測試維持綠燈（必要時更新測試以反映新模型）"
      ],
      "history": [
        { "timestamp": "2026-06-16T00:00:00Z", "automated_tests": "PASS", "ai_verification": "PASS: 重寫 init/gate 為家長(Gmail stub)→家長首頁→小孩 三段流程。新增 cloudStore(本機，介面對齊 Supabase)+auth.signInWithGoogle；parentGoogleLogin/createChildSubmit/enterChild/exitChild/parentLogout/migrateFlatAccountsToCloud；save() 鏡射活躍小孩 blob 到 parent.children[]；boot() 依 session 路由；topbar switchAccount→exitChild；家長頁 renderAccounts 改管理小孩(刪除/切換/登出家長)；setMyPassword 改提示(小孩免密碼)。小孩端唯一出口 exitChild(無法登出家長)；parent-home 有小孩時隱藏登出家長(只在 PIN 保護的家長頁)。舊扁平帳號一次性遷移為本機家長名下小孩。測試：smoke 77/77、cloud-store 9/9、accounts(新模型) 8/8、desktop-save 4/4 全綠。" }
      ]
    },
    {
      "id": 18,
      "title": "家長後台：任務審核佇列 + 小孩送出即時通知",
      "spec_file": "milestones/m18-parent-approval-notify.md",
      "spec_summary": "小孩按下『完成家事/任務』→ 進入該家長的待審核佇列並產生通知（紅點/橫幅）；家長頁面集中審核自己名下每個小孩的任務，核准發獎、退回不發。即時通知本機以輪詢/狀態旗標實作，雲端就緒（日後可換 Supabase Realtime / 推播）。",
      "status": "complete",
      "attempts": 1,
      "max_attempts": 3,
      "require_human_approval": false,
      "depends_on": [17],
      "human_feedback": null,
      "acceptance_criteria": [
        "小孩標記任務完成 → 立即進入家長待審核佇列，家長端出現未讀通知（紅點+數量）",
        "家長頁面可逐筆核准/退回自己名下任一小孩的任務；核准才發 EXP/金幣",
        "通知與佇列以 cloudStore 抽象層儲存，雲端缺失時走本機輪詢；介面對齊未來 Realtime/推播",
        "新增對應自動化測試（佇列進出、核准發獎、退回不發），全測試綠燈"
      ],
      "history": [
        { "timestamp": "2026-06-16T00:00:00Z", "automated_tests": "PASS", "ai_verification": "PASS: 家長審核佇列由各小孩 blob/活躍 live state 推導（childPendingTasks/parentQueue/parentPendingCount），與 save() 即時鏡射搭配恆一致、不會 desync。家長首頁每個小孩卡顯示 🔔 待審核紅點數與『審核』鈕＋頂部總數行；reviewChild 進入該小孩審核頁(parentUnlocked=true,goScreen parent)重用既有 approveTask/rejectTask 核准發獎/退回不發。本地『即時』＝進家長首頁即見最新；真正推播留 M23。新增 test/parent-queue.test.js 7/7；smoke 77、cloud-store 9、accounts 8、desktop 4 全綠。" }
      ]
    },
    {
      "id": 19,
      "title": "遊戲架構重整：金錢/等級/升級曲線/任務主線+支線（6–15 歲台灣社會觀）",
      "spec_file": "milestones/m19-game-progression-architecture.md",
      "spec_summary": "重整經濟與成長：金錢架構、等級架構、Lv0→100 升級曲線、任務主線（成長敘事）+ 支線（日常家事/學習）。內容符合 6–15 歲台灣家庭與校園價值觀，機制鼓勵『今天比昨天更好』（成長對比、連續、每日目標）。沿用並擴充 M12 ECONOMY。",
      "status": "pending",
      "attempts": 1,
      "max_attempts": 3,
      "require_human_approval": false,
      "depends_on": [12, 17],
      "human_feedback": null,
      "acceptance_criteria": [
        "明確的金錢架構與來源/去向；等級 1→100 升級曲線經數值定義且可被速通驗證",
        "任務分主線（章節式成長敘事）與支線（每日家事/學習），各有適齡（6–15）內容與台灣在地情境",
        "成長機制鼓勵『今天比昨天更好』：每日目標、個人最佳、連續成長獎勵，避免懲罰/羞辱式設計",
        "經濟/等級平衡通過 M20 速通驗證，無明顯卡關或通膨；全測試綠燈"
      ],
      "history": []
    },
    {
      "id": 20,
      "title": "測試/除錯模式：無限金幣 + 等級 0→100 速通與平衡驗證",
      "spec_file": "milestones/m20-debug-playtest-mode.md",
      "spec_summary": "家長隱藏的除錯模式：無限金幣、一鍵跳級、模擬每日完成，自動跑過 Lv0→100 全程，輸出各階段所需任務數/天數/金幣收支報告，找出卡關與通膨點並回饋 M19 調整。除錯入口不可被小孩開啟。",
      "status": "pending",
      "attempts": 1,
      "max_attempts": 3,
      "require_human_approval": false,
      "depends_on": [19],
      "human_feedback": null,
      "acceptance_criteria": [
        "除錯模式提供無限金幣與跳級，僅家長可進入（小孩端無入口）",
        "可自動模擬 Lv0→100 全程並輸出每階段任務數/天數/金幣收支/解鎖節點報告",
        "依報告找出至少卡關/通膨問題並回饋 M19 調整，再次驗證改善",
        "除錯資料不污染正式存檔；全測試綠燈"
      ],
      "history": []
    },
    {
      "id": 21,
      "title": "世界戰績排行榜（跨家庭，雲端就緒）",
      "spec_file": "milestones/m21-world-leaderboard.md",
      "spec_summary": "不同家長名下的小孩可在世界排行榜互相看到（等級/戰績/成就），含篩選與名次。先以 cloudStore 抽象層 + 本機示範資料實作，介面與資料形態對齊未來 Supabase 公開讀取表。僅公開非敏感資訊（暱稱/等級/戰績），不露個資。",
      "status": "pending",
      "attempts": 1,
      "max_attempts": 3,
      "require_human_approval": false,
      "depends_on": [17, 19],
      "human_feedback": null,
      "acceptance_criteria": [
        "排行榜顯示跨家庭小孩的暱稱/等級/戰績/名次，可篩選（總榜/週榜/同齡）",
        "只公開非敏感資訊；不顯示真實姓名/email/家長資訊",
        "以 cloudStore 抽象層讀取，本機以示範資料運作，介面對齊未來公開讀取表",
        "全測試綠燈"
      ],
      "history": []
    },
    {
      "id": 22,
      "title": "跨家庭虛擬物品交換（交易系統，雲端就緒）",
      "spec_file": "milestones/m22-item-trading.md",
      "spec_summary": "不同家庭的小孩可交換虛擬物品：提出交易→對方接受→雙方背包更新，含家長可選的核可開關防止不當交易。先本機抽象層 + 示範對手實作，介面對齊未來 Supabase 交易表/交易狀態機。",
      "status": "pending",
      "attempts": 1,
      "max_attempts": 3,
      "require_human_approval": false,
      "depends_on": [21],
      "human_feedback": null,
      "acceptance_criteria": [
        "小孩可對另一家庭小孩提出物品交換，對方接受後雙方背包正確更新（交易狀態機：proposed→accepted/declined/cancelled）",
        "家長可開啟交易核可開關，需家長同意才成交（防詐騙/不當交易）",
        "以 cloudStore 抽象層實作，本機以示範對手運作，介面對齊未來交易表",
        "交易不會憑空增減物品（守恆）；全測試綠燈"
      ],
      "history": []
    },
    {
      "id": 23,
      "title": "真正的雲端接線：Supabase + Google OAuth（human-approval gate）",
      "spec_file": "milestones/m23-supabase-google-wire.md",
      "spec_summary": "把 cloudStore 抽象層接到真正的 Supabase（家長帳號表/小孩子表/任務佇列/排行榜/交易表 + RLS）與 Google OAuth 家長登入。需使用者建立 Supabase 專案與 Google OAuth 憑證並提供金鑰（環境變數，不進 repo）。在此之前全系統以本機降級運作。",
      "status": "pending",
      "attempts": 1,
      "max_attempts": 3,
      "require_human_approval": true,
      "depends_on": [17, 18, 21, 22],
      "human_feedback": "2026-06-16 使用者已先提供部分公開金鑰（存於 gitignore 的 cloud-config.local.json）：siteUrl=https://allrisekids.vercel.app、supabasePublishableKey=sb_publishable_…、googleClientId=541985626153-…。仍缺 Supabase Project URL（https://<ref>.supabase.co）才能接線；並待確認 Supabase Google provider 已 Enable+Client Secret、Google redirect URIs 含 supabase callback。M23 deps（M17/M18/M21/M22）尚未完成，先擱置，到位後再接。",
      "acceptance_criteria": [
        "Supabase 專案建立、schema（家長/小孩/佇列/排行榜/交易 + RLS）部署，金鑰以環境變數注入不進 repo",
        "家長以真實 Google 帳號登入；不同家長資料以 RLS 隔離",
        "cloudStore 抽象層切換到 Supabase 後，帳號/任務審核/排行榜/交易跨裝置同步正常",
        "雲端設定缺失時自動退回本機且全測試維持綠燈"
      ],
      "history": []
    }
  ]
}
